nexus_sdk-0.3.2.data/data/LICENSE.txt
nexussdk/__init__.py
nexussdk/acls.py
nexussdk/config.py
nexussdk/files.py
nexussdk/identities.py
nexussdk/organizations.py
nexussdk/permissions.py
nexussdk/projects.py
nexussdk/realms.py
nexussdk/resolvers.py
nexussdk/resources.py
nexussdk/schemas.py
nexussdk/storages.py
nexussdk/views.py
nexussdk/utils/__init__.py
nexussdk/utils/genericmap.py
nexussdk/utils/http.py
nexussdk/utils/store.py
nexussdk/utils/tools.py
tests/__init__.py
tests/test_attachment_prod.py
tests/test_files.py
tests/test_import.py
tests/test_organization.py
tests/test_project.py
tests/test_resource.py
tests/test_schema.py
tests/test_views.py
nexus_sdk-0.3.2.dist-info/LICENSE.txt
nexus_sdk-0.3.2.dist-info/METADATA
nexus_sdk-0.3.2.dist-info/WHEEL
nexus_sdk-0.3.2.dist-info/top_level.txt
nexus_sdk-0.3.2.dist-info/RECORD
